anomasota/__init__.py
anomasota-0.0.0.dist-info/LICENSE
anomasota-0.0.0.dist-info/METADATA
anomasota-0.0.0.dist-info/WHEEL
anomasota-0.0.0.dist-info/top_level.txt
anomasota-0.0.0.dist-info/RECORD
